lhcbdiracx/client/__init__.py
lhcbdiracx/client/aio.py
lhcbdiracx/client/models.py
lhcbdiracx/client/py.typed
lhcbdiracx/client/sync.py
lhcbdiracx/client/_generated/__init__.py
lhcbdiracx/client/_generated/_client.py
lhcbdiracx/client/_generated/_configuration.py
lhcbdiracx/client/_generated/_patch.py
lhcbdiracx/client/_generated/_serialization.py
lhcbdiracx/client/_generated/_vendor.py
lhcbdiracx/client/_generated/py.typed
lhcbdiracx/client/_generated/_utils/__init__.py
lhcbdiracx/client/_generated/_utils/serialization.py
lhcbdiracx/client/_generated/_utils/utils.py
lhcbdiracx/client/_generated/aio/__init__.py
lhcbdiracx/client/_generated/aio/_client.py
lhcbdiracx/client/_generated/aio/_configuration.py
lhcbdiracx/client/_generated/aio/_patch.py
lhcbdiracx/client/_generated/aio/_vendor.py
lhcbdiracx/client/_generated/aio/operations/__init__.py
lhcbdiracx/client/_generated/aio/operations/_operations.py
lhcbdiracx/client/_generated/aio/operations/_patch.py
lhcbdiracx/client/_generated/models/__init__.py
lhcbdiracx/client/_generated/models/_enums.py
lhcbdiracx/client/_generated/models/_models.py
lhcbdiracx/client/_generated/operations/__init__.py
lhcbdiracx/client/_generated/operations/_operations.py
lhcbdiracx/client/_generated/operations/_patch.py
lhcbdiracx_client-0.0.7.dist-info/METADATA
lhcbdiracx_client-0.0.7.dist-info/WHEEL
lhcbdiracx_client-0.0.7.dist-info/entry_points.txt
lhcbdiracx_client-0.0.7.dist-info/top_level.txt
lhcbdiracx_client-0.0.7.dist-info/RECORD
