Metadata-Version: 2.4
Name: lhcbdiracx-client
Version: 0.0.7
Summary: TODO
License: GPL-3.0-only
Classifier: Intended Audience :: Science/Research
Classifier: License :: OSI Approved :: GNU General Public License v3 (GPLv3)
Classifier: Programming Language :: Python :: 3
Classifier: Topic :: Scientific/Engineering
Classifier: Topic :: System :: Distributed Computing
Requires-Python: >=3.11
Requires-Dist: lhcbdiracx-core
Requires-Dist: diracx-client==0.0.7
Provides-Extra: types
Requires-Dist: types-requests; extra == "types"
Requires-Dist: diracx-api[types]==0.0.7; extra == "types"
Provides-Extra: testing
Requires-Dist: diracx-client[testing]==0.0.7; extra == "testing"
Requires-Dist: diracx-testing==0.0.7; extra == "testing"
